{
  "locations":[
    {
      "id":1,
      "name":"Arandis"
    },
    {
      "id":2,
      "name":"Aranos"
    },
    {
      "id":3,
      "name":"Eenhana"
    },
    {
      "id":4,
      "name":"Gobabis"
    },
    {
      "id":5,
      "name":"Helao Nafidi"
    },
    {
      "id":6,
      "name":"Henties Bay"
    },
    {
      "id":5,
      "name":"Karasburg"
    },
    {
      "id":7,
      "name":"Karibib"
    },
    {
      "id":8,
      "name":"Karasburg"
    },
    {
      "id":9,
      "name":"Katima Mulilo"
    },
    {
      "id":10,
      "name":"Keetmanshoop"
    },
    {
      "id":11,
      "name":"Khorixas"
    },
    {
      "id":12,
      "name":"Mariental"
    },
    {
      "id":13,
      "name":"Okahao"
    },
    {
      "id":14,
      "name":"Okahandja"
    },
    {
      "id":15,
      "name":"Okakarara"
    },
    {
      "id":16,
      "name":"Okakarara"
    },
    {
      "id":17,
      "name":"Omaruru"
    },
    {
      "id":18,
      "name":"Omuthiya"
    },
    {
      "id":19,
      "name":"Ondangwa"
    },
    {
      "id":20,
      "name":"Ongwediva"
    },
    {
      "id":21,
      "name":"Opuwo"
    },
    {
      "id":22,
      "name":"Oshakati"
    },
    {
      "id":23,
      "name":"Oshikuku"
    },
    {
      "id":24,
      "name":"Otavi"
    },
    {
      "id":25,
      "name":"Otjiwarongo"
    },
    {
      "id":26,
      "name":"Outapi"
    },
    {
      "id":27,
      "name":"Outjo"
    },
    {
      "id":28,
      "name":"Rehoboth"
    },
    {
      "id":29,
      "name":"Ruacan"
    },
    {
      "id":30,
      "name":"Rundu"
    },
    {
      "id":31,
      "name":"Swakopmund"
    },
    {
      "id":32,
      "name":"Tsumeb"
    },
    {
      "id":33,
      "name":"Usakos"
    },
    {
      "id":34,
      "name":"Walvis Bay"
    },
    {
      "id":35,
      "name":"Windhoek"
    }
  ],
  "categories":[
    {
      "id":1,
      "name": "Ambulance"
    },
    {
      "id":2,
      "name": "Fire Brigade"
    },
    {
      "id":3,
      "name": "Neighbourhood Watch"
    },
    {
      "id":4,
      "name": "Police"
    },
    {
      "id":5,
      "name": "Car Tow Service"
    }
  ],
  "services":[
    {
      "id":1,
      "name":"City of Windhoek Ambulance Services",
      "category":{
        "id":1,
        "name": "Ambulance"
      },
      "contact":"+264 61 290 2833",
      "location":{
        "id":35,
        "name":"Windhoek"
      }
    },
    {
      "id":2,
      "name":"E-Med Rescue 24",
      "category":{
        "id":1,
        "name": "Ambulance"
      },
      "contact":"+264 83 924",
      "location":{
        "id":35,
        "name":"Windhoek"
      }
    },
    {
      "id":3,
      "name":"Otjomuise Fire Station",
      "category":{
        "id":2,
        "name": "Fire Brigade"
      },
      "contact":"061 290 3381",
      "location":{
        "id":35,
        "name":"Windhoek"
      }
    },
    {
      "id":4,
      "name":"Diaz Fire Station",
      "category":{
        "id":2,
        "name": "Fire Brigade"
      },
      "contact":"061 250 084",
      "location":{
        "id":35,
        "name":"Windhoek"
      }
    },
    {
      "id":5,
      "name":"Pioneerspark Neighbourhood Watch (PPNHW)",
      "category":{
        "id":3,
        "name": "Neighbourhood Watch"
      },
      "contact":"081 299 8888",
      "location":{
        "id":35,
        "name":"Windhoek"
      }
    },
    {
      "id":6,
      "name":"Fidel Castro Neighbourhood Watch",
      "category":{
        "id":3,
        "name": "Neighbourhood Watch"
      },
      "contact":"081 338 8737",
      "location":{
        "id":35,
        "name":"Windhoek"
      }
    },
    {
      "id":7,
      "name":"Windhoek City Police Service",
      "category":{
        "id":4,
        "name": "Police"
      },
      "contact":"061 290 2239",
      "location":{
        "id":35,
        "name":"Windhoek"
      }
    },
    {
      "id":8,
      "name":"MRT - Towing and Transport",
      "category":{
        "id":5,
        "name": "Car Tow Service"
      },
      "contact":"081 032 3000",
      "location":{
        "id":35,
        "name":"Windhoek"
      }
    },
    {
      "id":9,
      "name":"A&A Recovery & Tow-in Service",
      "category":{
        "id":5,
        "name": "Car Tow Service"
      },
      "contact":"081 122 5311",
      "location":{
        "id":35,
        "name":"Windhoek"
      }
    },
    {
      "id":10,
      "name":"Namibia 24 Road Assistance",
      "category":{
        "id":5,
        "name": "Car Tow Service"
      },
      "contact":"081 148 7812",
      "location":{
        "id":35,
        "name":"Windhoek"
      }
    }
  ]
}
